Workbook

Sheet Financials
A1: Financials
A3: Income Statement
A4: ₹ Crores | B4: FY22 | C4: FY23 | D4: FY24 | E4: FY25 | F4: FY26
A5: Revenue | B5: 778.96 | C5: 973.98 | D5: 1243.83 | E5: 1486.88 | F5: 1574.4
A6: Other Income | B6: 29.91 | C6: 33.99 | D6: 48.06 | E6: 63.58 | F6: 67.01
A7: YoY Growth | B7: — | C7: 0.2504 | D7: 0.2771 | E7: 0.1954 | F7: 0.0589
A8: EBITDA | B8: 194.66 | C8: 212.21 | D8: 288.31 | E8: 376.21 | F8: 405.8
A9: EBITDA Margin | B9: 0.2499 | C9: 0.2179 | D9: 0.2318 | E9: 0.253 | F9: 0.2577
A10: EBIT | B10: 177.03 | C10: 187.54 | D10: 260.34 | E10: 343.17 | F10: 369.2
A11: EBIT Margin | B11: 0.2273 | C11: 0.1925 | D11: 0.2093 | E11: 0.2308 | F11: 0.2345
A12: Reported PAT | B12: 164.21 | C12: 177.01 | D12: 251.61 | E12: 315.24 | F12: 300.58
A13: PAT Margin | B13: 0.2108 | C13: 0.1817 | D13: 0.2023 | E13: 0.212 | F13: 0.1909
A14: Diluted EPS | B14: 11.75 | C14: 12.5 | D14: 17.5 | E14: 21.89 | F14: 21.24
A16: Cash Flow
A17: ₹ Crores | B17: FY22 | C17: FY23 | D17: FY24 | E17: FY25 | F17: FY26
A18: CFO | B18: 142.77 | C18: 136.35 | D18: 281.41 | E18: 214.98 | F18: 231.86
A19: Capex | B19: 12.69 | C19: 16.77 | D19: 13.81 | E19: 23.35 | F19: 9.75
A20: Free Cash Flow | B20: 130.08 | C20: 119.58 | D20: 267.6 | E20: 191.63 | F20: 222.11
A21: FCF Margin | B21: 0.167 | C21: 0.1228 | D21: 0.2151 | E21: 0.1289 | F21: 0.1411
A23: Operating Metrics
A24: ₹ Crores/Count | B24: FY22 | C24: FY23 | D24: FY24 | E24: FY25 | F24: FY26
A25: Subscription Revenue | B25: 246.1 | C25: 322.7 | D25: 373.15 | E25: 431.2 | F25: 525
A26: SaaS Revenue | B26: 61.8 | C26: 100 | D26: 124.38 | E26: 148.69 | F26: 202.22
A27: Annuity Revenue | B27: 456.5 | C27: 594.5 | D27: 749.8 | E27: 833.75 | F27: 968
A28: Subscription % of Revenue | B28: =B25/B5 -> 0.31593407 | C28: =C25/C5 -> 0.33132097 | D28: =D25/D5 -> 0.3000008 | E28: =E25/E5 -> 0.29000323 | F28: =F25/F5 -> 0.33346037
A29: Annuity % of Revenue | B29: =B27/B5 -> 0.58603779 | C29: =C27/C5 -> 0.61038214 | D29: =D27/D5 -> 0.6028155 | E29: =E27/E5 -> 0.56073792 | F29: =F27/F5 -> 0.6148374
A30: New Logos | B30: 38 | C30: 47 | D30: 51 | E30: 62 | F30: 47
A31: Customers > ₹5 Cr Billing | B31: 38 | C31: 51 | D31: 65 | E31: 87 | F31: 101
A33: Growth Metrics
A34: Metric | B34: FY22 | C34: FY23 | D34: FY24 | E34: FY25 | F34: FY26
A35: Subscription Revenue Growth | B35: — | C35: =C25/B25-1 -> 0.31125559 | D35: =D25/C25-1 -> 0.15633716 | E35: =E25/D25-1 -> 0.15556747 | F35: =F25/E25-1 -> 0.21753247
A36: Annuity Revenue Growth | B36: — | C36: =C27/B27-1 -> 0.30230011 | D36: =D27/C27-1 -> 0.26122792 | E36: =E27/D27-1 -> 0.11196319 | F36: =F27/E27-1 -> 0.16101949
A37: Customers > ₹5 Cr Growth | B37: — | C37: =C31/B31-1 -> 0.34210526 | D37: =D31/C31-1 -> 0.2745098 | E37: =E31/D31-1 -> 0.33846154 | F37: =F31/E31-1 -> 0.16091954

Sheet DCF
A1: DCF
A3: Metric | B3: FY27E | C3: FY28E | D3: FY29E | E3: FY30E | F3: FY31E
A4: Revenue Growth | B4: 0.12 | C4: 0.1 | D4: 0.09 | E4: 0.08 | F4: 0.07
A5: Revenue | B5: =Financials!F5*(1+B4) -> 1763.328 | C5: =B5*(1+C4) -> 1939.6608 | D5: =C5*(1+D4) -> 2114.2303 | E5: =D5*(1+E4) -> 2283.3687 | F5: =E5*(1+F4) -> 2443.2045
A6: EBITDA Margin | B6: 0.27 | C6: 0.28 | D6: 0.29 | E6: 0.3 | F6: 0.305
A7: EBITDA | B7: =B5*B6 -> 476.09856 | C7: =C5*C6 -> 543.10502 | D7: =D5*D6 -> 613.12678 | E7: =E5*E6 -> 685.01061 | F7: =F5*F6 -> 745.17737
A8: D&A % Revenue | B8: 0.025 | C8: 0.025 | D8: 0.025 | E8: 0.025 | F8: 0.025
A9: EBIT | B9: =B7-(B5*B8) -> 432.01536 | C9: =C7-(C5*C8) -> 494.6135 | D9: =D7-(D5*D8) -> 560.27102 | E9: =E7-(E5*E8) -> 627.92639 | F9: =F7-(F5*F8) -> 684.09726
A10: Tax Rate | B10: 0.25 | C10: 0.25 | D10: 0.25 | E10: 0.25 | F10: 0.25
A11: Tax on EBIT | B11: =B9*B10 -> 108.00384 | C11: =C9*C10 -> 123.65338 | D11: =D9*D10 -> 140.06776 | E11: =E9*E10 -> 156.9816 | F11: =F9*F10 -> 171.02432
A12: NOPAT | B12: =B9-B11 -> 324.01152 | C12: =C9-C11 -> 370.96013 | D12: =D9-D11 -> 420.20327 | E12: =E9-E11 -> 470.94479 | F12: =F9-F11 -> 513.07295
A14: Capex % Revenue | B14: 0.015 | C14: 0.015 | D14: 0.015 | E14: 0.015 | F14: 0.015
A15: Capex | B15: =B5*B14 -> 26.44992 | C15: =C5*C14 -> 29.094912 | D15: =D5*D14 -> 31.713454 | E15: =E5*E14 -> 34.25053 | F15: =F5*F14 -> 36.648068
A17: Change in NWC % Revenue | B17: 0.02 | C17: 0.02 | D17: 0.02 | E17: 0.02 | F17: 0.02
A18: Change in NWC | B18: =B5*B17 -> 35.26656 | C18: =C5*C17 -> 38.793216 | D18: =D5*D17 -> 42.284605 | E18: =E5*E17 -> 45.667374 | F18: =F5*F17 -> 48.86409
A20: FCFF | B20: =B12+(B5*B8)-B15-B18 -> 306.37824 | C20: =C12+(C5*C8)-C15-C18 -> 351.56352 | D20: =D12+(D5*D8)-D15-D18 -> 399.06096 | E20: =E12+(E5*E8)-E15-E18 -> 448.11111 | F20: =F12+(F5*F8)-F15-F18 -> 488.6409
A22: WACC Calculation
A23: Risk-Free Rate | B23: 0.0707
A24: Beta | B24: 1
A25: Market Risk Premium | B25: 0.065
A26: Cost of Equity | B26: =B23+B24*B25 -> 0.1357
A27: Cost of Debt | B27: 0
A28: Debt / Capital | B28: 0
A29: Equity / Capital | B29: 1
A30: WACC | B30: =B26*B29+B27*B28 -> 0.1357
A32: Terminal Growth Rate | B32: 0.045
A34: PV of FCFF | B34: =B20/(1+$B$30)^1 -> 269.7704 | C34: =C20/(1+$B$30)^2 -> 272.56906 | D34: =D20/(1+$B$30)^3 -> 272.42588 | E34: =E20/(1+$B$30)^4 -> 269.35882 | F34: =F20/(1+$B$30)^5 -> 258.6257
A36: Terminal Value | F36: =F20*(1+$B$32)/($B$30-$B$32) -> 5629.8759
A37: PV of Terminal Value | F37: =F36/(1+$B$30)^5 -> 2979.7559
A39: Enterprise Value | B39: =SUM(B34:F34)+F37 -> 4322.5058
A41: Cash & Investments | B41: =103.53+307.99+703.08 -> 1114.6
A42: Debt | B42: 0
A43: Net Cash | B43: =B41-B42 -> 1114.6
A44: Equity Value | B44: =B39+B43 -> 5437.1058
A46: Shares Outstanding (Cr) | B46: =Financials!F12/Financials!F14 -> 14.151601
A47: Implied Share Price | B47: =B44/B46 -> 384.20429
A48: Current Share Price | B48: 486.6
A49: Upside / (Downside) | B49: =B47/B48-1 -> -0.21043096

Sheet Comps
A1: Trading Comparables
A3: Company | B3: Share Price | C3: Market Cap (₹ Cr) | D3: Enterprise Value (₹ Cr) | E3: Revenue (₹ Cr) | F3: EBITDA (₹ Cr) | G3: P/E | H3: EV/EBITDA
A4: Newgen Software | B4: =DCF!B48 -> 486.6 | C4: =486.6*14.15 -> 6885.39 | D4: 5785 | E4: =Financials!F5 -> 1574.4 | F4: =Financials!F8 -> 405.8 | G4: =21.83 -> 21.83 | H4: =13.72 -> 13.72
A5: Persistent Systems | B5: 5266.5 | C5: 78759.2 | D5: 77391.2 | E5: 15718.1 | F5: 2957.05 | G5: 43.2 | H5: 26.17
A6: Coforge | B6: 1782 | C6: 78956.4 | D6: 78728 | E6: 18226 | F6: 3598.17 | G6: 36.51 | H6: 21.88
A7: Mphasis | B7: 2237.2 | C7: 42967.5 | D7: 42406.4 | E7: 16531.2 | F7: 3033.93 | G7: 22.49 | H7: 13.98
A8: OFSS | B8: 10905 | C8: 94468.2 | D8: 89734.1 | E8: 8945.1 | F8: 4507.08 | G8: 27.68 | H8: 19.91
A10: Peer Median | G10: =MEDIAN(G5:G8) -> 32.095 | H10: =MEDIAN(H5:H8) -> 20.895
A12: EV/EBITDA Valuation | D12: P/E Valuation
A13: Peer Median EV/EBITDA | B13: =H10 -> 20.895 | D13: Peer Median P/E | E13: =G10 -> 32.095
A14: Newgen FY26 EBITDA | B14: =Financials!F8 -> 405.8 | D14: Newgen FY26 PAT | E14: =Financials!F12 -> 300.58
A15: Implied Enterprise Value | B15: =B13*B14 -> 8479.191 | D15: Implied Equity Value | E15: =E13*E14 -> 9647.1151
A16: Net Cash | B16: =DCF!B43 -> 1114.6 | D16: Shares Outstanding (Cr) | E16: =DCF!B46 -> 14.151601
A17: Implied Equity Value | B17: =B15+B16 -> 9593.791 | D17: Implied Share Price | E17: =E15/E16 -> 681.6978
A18: Shares Outstanding (Cr) | B18: =DCF!B46 -> 14.151601
A19: Implied Share Price | B19: =B17/B18 -> 677.92974

Sheet Industry
A1: Industry Overview
A3: Market Opportunity
A4: India Digital Transformation Market | B4: 46.42 | C4: $bn, 2025
A5: India Digital Transformation Market | B5: 99.37 | C5: $bn, 2030
A6: Market CAGR | B6: 0.135 | C6: 2025–30
A7: India Software Spendin | B7: 24.7 | C7: $bn, 2026
A8: Software Spending Growth | B8: 0.176 | C8: YoY, 2026
A10: Key Growth Drivers
A11: AI & Generative AI | B11: High
A12: Cloud Adoption | B12: High
A13: Low-Code / Automation | B13: High
A14: Enterprise Digitalization | B14: High
A15: Process Modernization | B15: High
A17: Newgen Industry Exposure
A18: FY26 Revenue | B18: 1574.4
A19: FY26 Annuity Revenue | B19: 968
A20: FY26 Subscription Revenue | B20: 525
A21: SaaS Growth | B21: 0.36
A22: New Logos | B22: 47
A23: Customers > ₹5 Cr | B23: 101
A24: US Revenue Growth | B24: 0.17
A25: APAC Revenue Growth | B25: 0.14
A27: Competitive Position
A28: Core Platform | B28: NewgenONE
A29: Low-Code | B29: Yes
A30: AI / ML | B30: Yes
A31: Intelligent Document Processing | B31: Yes
A32: Content Management | B32: Yes
A33: Process Automation | B33: Yes
A34: Key Verticals | B34: BFSI / Government / Healthcare

Sheet Research
A1: Investment Research
A3: Investment Thesis
A4: Revenue Growth | B4: FY22–FY26 Revenue CAGR | C4: =(Financials!F5/Financials!B5)^(1/4)-1 -> 0.19233964
A5: Recurring Revenue | B5: FY26 Annuity Revenue | C5: 968
A6: Subscription Growth | B6: FY26 YoY Growth | C6: 0.24
A7: SaaS Growth | B7: FY26 YoY Growth | C7: 0.36
A8: Large Customers | B8: >₹5 Cr Billing | C8: 101
A10: Key Catalysts
A11: AI Monetization | B11: Agentic AI embedded in NewgenONE
A12: SaaS Expansion | B12: SaaS growth +36% YoY
A13: Subscription Mix | B13: Subscription revenue +24% YoY
A14: Customer Expansion | B14: 101 customers >₹5 Cr
A15: US Expansion | B15: US revenue +17% YoY
A16: Product Recognition | B16: 67 patents filed to date
A18: Competitive Advantages
A19: Unified Platform | B19: Content + Process + Communication + AI
A20: Low-Code | B20: Enterprise application development
A21: Industry Focus | B21: BFSI / Government / Healthcare
A22: Recurring Revenue | B22: ₹968 Cr annuity revenue
A23: Customer Stickiness | B23: 101 customers >₹5 Cr billing
A25: Key Risks
A26: Revenue Growth | B26: FY26 revenue growth slowed to 6%
A27: Competition | B27: Global & Indian software vendors
A28: AI Execution | B28: Monetization of AI investments
A29: International Exposure | B29: US / international demand sensitivity
A30: Talent | B30: Dependence on skilled technology professionals
A31: Valuation | B31: DCF below current market price
A33: Core Thesis | B33: Recurring revenue + SaaS + AI can drive a higher-quality growth mix and support margin expansion.
A34: Key Debate | B34: Can subscription/SaaS growth offset slower overall revenue growth?

Sheet Pitch
A1: Investment Pitch
A3: Slide # | B3: Slide Title | C3: Key Message | D3: Supporting Data | E3: Visual
A4: 1 | B4: Investment Thesis | C4: Recurring revenue, SaaS growth and AI create a potential path to higher-quality growth | D4: FY22–FY26 Revenue CAGR: 19.23%; FY26 SaaS growth: 36%; Annuity: ₹968 Cr
A5: 2 | B5: Company Overview | C5: Newgen provides enterprise workflow, content and automation software | D5: FY26 Revenue: ₹1,574 Cr; 101 customers >₹5 Cr billing
A6: 3 | B6: Industry Opportunity | C6: Digital transformation and enterprise software spending remain structural growth drivers | D6: India digital transformation market: $46.42bn → $99.37bn; 13.5% CAGR
A7: 4 | B7: Growth Engine | C7: Subscription, SaaS and international expansion are reshaping the revenue mix | D7: Subscription: ₹525 Cr; Annuity: ₹968 Cr; US growth: 17%
A8: 5 | B8: Financial Performance | C8: Revenue compounded strongly while EBITDA margins have recovered | D8: FY26 EBITDA: ₹405.8 Cr; EBITDA margin: 25.77%
A9: 6 | B9: Competitive Position | C9: Newgen combines low-code, content, process automation and AI on one platform | D9: NewgenONE; Low-code; AI/ML; Content; Process Automation
A10: 7 | B10: Valuation | C10: DCF and trading comps provide different valuation reference points | D10: DCF: ₹384; EV/EBITDA: ₹678; P/E: ₹682
A11: 8 | B11: Catalysts | C11: SaaS growth, AI monetization and customer expansion are key potential catalysts | D11: SaaS +36%; Subscription +24%; US revenue +17%; 101 customers >₹5 Cr
A12: 9 | B12: Risks | C12: Slower headline growth and AI execution create important downside considerations | D12: FY26 revenue growth: 6%; DCF below market price; AI monetization risk
A13: 10 | B13: Valuation Summary | C13: DCF, P/E and EV/EBITDA provide a range of valuation reference points | D13: DCF: ₹384 | EV/EBITDA: ₹678 | P/E: ₹682
